pecat/__init__.py
pecat/__main__.py
pecat/test.py
pecat-0.0.2.dist-info/LICENSE
pecat-0.0.2.dist-info/METADATA
pecat-0.0.2.dist-info/WHEEL
pecat-0.0.2.dist-info/top_level.txt
pecat-0.0.2.dist-info/RECORD
